geoelement/__init__.py
geoelement/common.py
geoelement/geoelement.py
geoelement-0.0.2.dist-info/LICENSE
geoelement-0.0.2.dist-info/METADATA
geoelement-0.0.2.dist-info/WHEEL
geoelement-0.0.2.dist-info/entry_points.txt
geoelement-0.0.2.dist-info/top_level.txt
geoelement-0.0.2.dist-info/RECORD
